{
  "id": "Xerox-Document_Homecentre",
  "manufacturer": "Xerox",
  "model": "Document Homecentre",
  "type": "inkjet",
  "functionality": "D",
  "notes": "Multifunction Printer/Scanner\n<br>Have not explored scanner functionality under Linux; almost certain no to work.\n<br>Works quite well as a 300x300 dpi color printer. \n<br>Printer Doc's claim 600x600 on special paper, but 300x300 on normalpaper looks good.<p>\n\n      Consumables/Refills: Indv. Ink Refills per color<p>",
  "drivers": [
    {
      "id": "cdj550",
      "name": "cdj550",
      "type": "other",
      "functionality": "?",
      "comments": "<B>This driver is available in the <A href=\"https://github.com/OpenPrinting/ghostscript-printer-app\">Ghostscript Printer Application</A></B><P>\n<iframe src=\"https://snapcraft.io/ghostscript-printer-app/embedded?button=black&summary=true\" frameborder=\"0\" width=\"100%\" height=\"300px\" style=\"border: 1px solid #CCC; border-radius: 2px;\"></iframe>",
      "ppd": null,
      "supportLevel": null,
      "color": null
    }
  ]
}