{
  "id": "Apollo-P-2100",
  "manufacturer": "Apollo",
  "model": "P-2100",
  "type": "inkjet",
  "functionality": "A",
  "notes": "Apollo is a brand of HP, the printers use HP cartridges and papers, the\n    main difference is the special design of the printers.<p>\n\n    Comes only with a standard three-colour cartridge and prints black as\n    a mix of the three colours, you get either a black or a photo (black,\n    light cyan, light magenta) cartridge as an option.<p>\n\n    To get its maximum quality, use the HPIJS (\"hpijs-pcl3\")\n    driver. 600 dpi in colour is not supported by the\n    hardware.<p>",
  "drivers": [
    {
      "id": "hpijs-pcl3"
    }
  ]
}