{
  "id": "HP-LaserJet_4200",
  "manufacturer": "HP",
  "model": "LaserJet 4200",
  "type": "laser",
  "functionality": "A",
  "notes": "PostScript Level 3, PCL5, PCL6, HP-GL/2<p>\n\n    Up to 35 pages/min.\n\n    48/64 MB std, depending on flavour (416 MB max.).<p>\n\n    For basic printing functionality use the Postscript PPD.\n    For advanced functionality such as printer status, maintenance \n    features, scanning and photo card unload use the <a href=\"\n    http://hplipopensource.com/\">HPLIP driver</a> (which includes \n    HPIJS). <p>\n\n    Optional accessories are duplexer, additional trays up to 1500\n    sheet, hard drive, extra memory, ethernet adapter,\n    stapler/stacker.<p><p>\n\n      Consumables/Refills: Toner and drum in one cartridge (12000 pages)<p>",
  "drivers": [
    {
      "id": "hplip"
    }
  ]
}