{
  "id": "Lexmark-Winwriter_150c",
  "manufacturer": "Lexmark",
  "model": "Winwriter 150c",
  "type": "inkjet",
  "functionality": "D",
  "notes": "Pieter-Jan Vandormael (pjv at skynet dot be) has started\n    development of a <a\n    href=\"http://users.skynet.be/pjvh/ww150c/\">driver</a> for\n    this printer. One can at least print in black and white\n    now.<p>\n\n    Please test the driver (also on the other Winwriters) and direct\n    all bug reports, suggestions, and contributions to\n    Pieter-Jan.<p><p>\n\n      Consumables/Refills: 1 black and 1 color (CMY) cartridge<p>",
  "drivers": []
}