{
  "id": "Lexmark-Optra_Color_45",
  "manufacturer": "Lexmark",
  "model": "Optra Color 45",
  "type": "inkjet",
  "functionality": "A",
  "notes": "Also speaks PCL 5c.\n<br>CMYK or CMYKcm color printing.\n<br>Cartridge loading/alignment/etc requires <a href=\"http://pup.sourceforge.net/\">PUP</a>\n<br>Model 45n includes network interface.\n<br>Also sold by Xerox as the <a href=\"show_printer.cgi?recnum=Xerox-DocuPrint_C20\">Docuprint C20</a><p>\n\n      Consumables/Refills: 4 or 6 color ink cartridge or bw only cartridge<p>",
  "drivers": [
    {
      "id": "Postscript"
    }
  ]
}